dicube-0.3.0.dist-info/METADATA
dicube-0.3.0.dist-info/WHEEL
dicube-0.3.0.dist-info/RECORD
dicube/__init__.py
dicube/validation.py
dicube/exceptions.py
dicube/codecs/__init__.py
dicube/codecs/jph/ojph_decode_complete.cpython-38-x86_64-linux-gnu.so
dicube/codecs/jph/ojph_complete.cpython-39-x86_64-linux-gnu.so
dicube/codecs/jph/__init__.py
dicube/codecs/jph/codec.py
dicube/codecs/jph/ojph_decode_complete.cpython-310-x86_64-linux-gnu.so
dicube/codecs/jph/ojph_decode_complete.cpython-39-x86_64-linux-gnu.so
dicube/codecs/jph/ojph_complete.cpython-310-x86_64-linux-gnu.so
dicube/codecs/jph/ojph_complete.cpython-38-x86_64-linux-gnu.so
dicube/utils/__init__.py
dicube/storage/__init__.py
dicube/storage/dcb_file.py
dicube/storage/pixel_utils.py
dicube/core/image.py
dicube/core/__init__.py
dicube/core/io.py
dicube/core/pixel_header.py
dicube/dicom/dicom_meta.py
dicube/dicom/dicom_status.py
dicube/dicom/merge_utils.py
dicube/dicom/dicom_builder.py
dicube/dicom/space_from_meta.py
dicube/dicom/__init__.py
dicube/dicom/dcb_streaming.py
dicube/dicom/dicom_tags.py
