Metadata-Version: 2.2
Name: dicube
Version: 0.3.0
Summary: Medical Image Storage Library with DICOM compatibility
Author: Fangzhou Liao
License: MIT
Classifier: Development Status :: 4 - Beta
Classifier: Intended Audience :: Healthcare Industry
Classifier: Intended Audience :: Science/Research
Classifier: License :: OSI Approved :: MIT License
Classifier: Operating System :: OS Independent
Classifier: Programming Language :: Python :: 3
Classifier: Programming Language :: Python :: 3.8
Classifier: Programming Language :: Python :: 3.9
Classifier: Programming Language :: Python :: 3.10
Classifier: Programming Language :: Python :: 3.11
Classifier: Programming Language :: Python :: 3.12
Classifier: Topic :: Scientific/Engineering :: Medical Science Apps.
Classifier: Topic :: Software Development :: Libraries :: Python Modules
Project-URL: Homepage, https://github.com/fastdiag-toolbox/dicube
Project-URL: Bug Reports, https://github.com/fastdiag-toolbox/dicube/issues
Project-URL: Source, https://github.com/fastdiag-toolbox/dicube
Requires-Python: >=3.8
Requires-Dist: numpy>=1.21.0
Requires-Dist: pydicom>=2.3.0
Requires-Dist: zstandard>=0.18.0
Requires-Dist: spacetransformer-core>=0.2.6
Provides-Extra: jph
Requires-Dist: pybind11<2.12.0,>=2.10.0; python_version < "3.9" and extra == "jph"
Requires-Dist: pybind11>=2.10.0; python_version >= "3.9" and extra == "jph"
Provides-Extra: nifti
Requires-Dist: nibabel>=3.2.0; extra == "nifti"
Provides-Extra: dev
Requires-Dist: pytest>=7.0.0; extra == "dev"
Requires-Dist: pytest-cov>=4.0.0; extra == "dev"
Requires-Dist: black>=22.0.0; extra == "dev"
Requires-Dist: ruff>=0.1.0; extra == "dev"
Requires-Dist: mypy>=1.0.0; extra == "dev"
Requires-Dist: build>=0.8.0; extra == "dev"
Requires-Dist: pylibjpeg>=2.0; extra == "dev"
Requires-Dist: pylibjpeg-openjpeg>=2.0; extra == "dev"
Requires-Dist: nibabel>=3.2.0; extra == "dev"
Provides-Extra: all
Requires-Dist: pybind11<2.12.0,>=2.10.0; python_version < "3.9" and extra == "all"
Requires-Dist: pybind11>=2.10.0; python_version >= "3.9" and extra == "all"
Requires-Dist: nibabel>=3.2.0; extra == "all"
